{
    "title": "CAMELs-DE data for gauge : DE111360 - Bebenhausen- discharge",
    "abstract": "The CAMELs-DE dataset provides a comprehensive collection of hydro-meteorological and catchment attributes data for 1582 streamflow gauges across Germany.",
    "external_id": "",
    "location": {
        "type": "Point",
        "bbox": null,
        "coordinates": [
            9.042629,
            48.55977999999999,
            null
        ]
    },
    "version": 1,
    "latest_version_id": null,
    "is_partial": false,
    "comment": "",
    "citation": "Dolich, A., Espinoza, E. A., Ebeling, P., Guse, B., Götte, J., Hassler, S., Hauffe, C., Kiesel, J., Heidbüchel, I., Mälicke, M., Müller-Thomy, H., Stölzle, M., Tarasova, L., & Loritz, R. (2024). CAMELS-DE: hydrometeorological time series and attributes for 1582 catchments in Germany (1.0.0) [Data set]. Zenodo. https://doi.org/10.5281/zenodo.13837553",
    "embargo": false,
    "embargo_end": null,
    "publication": "2024-07-23T00:00:00",
    "lastUpdate": "2024-09-25T00:00:00",
    "id": 5694,
    "uuid": "07f408ec-e1be-4c2d-9347-155b8a334463",
    "license": null,
    "variable": {
        "name": "discharge",
        "symbol": "Q",
        "column_names": [
            "discharge"
        ],
        "id": 4,
        "unit": {
            "name": "cubicmeter per second",
            "symbol": "m3/s",
            "si": "m^3*s^-1"
        },
        "keyword": {
            "id": 7327,
            "uuid": "36a2999b-2255-4d4e-a249-40df3b7b3aaf",
            "parent_id": 6220,
            "value": "DISCHARGE/FLOW",
            "full_path": "EARTH SCIENCE > TERRESTRIAL HYDROSPHERE > SURFACE WATER > SURFACE WATER PROCESSES/MEASUREMENTS > DISCHARGE/FLOW",
            "thesaurus": {
                "name": "GCMD",
                "title": "NASA/GCMD Earth Science Keywords",
                "organisation": "NASA",
                "url": "https://gcmdservices.gsfc.nasa.gov/kms/concepts/concept_scheme/sciencekeywords/?format=xml",
                "description": "NASA Global Clime change Master Dictionary Science Keywords",
                "uuid": "2e54668d-8fae-429f-a511-efe529420b12"
            }
        }
    },
    "author": {
        "is_organisation": false,
        "first_name": "Alexander",
        "last_name": "Dolich",
        "organisation_name": null,
        "organisation_abbrev": null,
        "affiliation": "Karlsruhe Institute of Technology",
        "attribution": null,
        "id": 28,
        "uuid": "9bd00305-c015-4a59-88d3-3d55ef4abbf2"
    },
    "coAuthors": [
        {
            "is_organisation": false,
            "first_name": "Alexander",
            "last_name": "Dolich",
            "organisation_name": null,
            "organisation_abbrev": null,
            "affiliation": "Karlsruhe Institute of Technology",
            "attribution": null,
            "id": 28,
            "uuid": "9bd00305-c015-4a59-88d3-3d55ef4abbf2"
        },
        {
            "is_organisation": false,
            "first_name": "Eduardo",
            "last_name": "Acuña Espinoza",
            "organisation_name": null,
            "organisation_abbrev": null,
            "affiliation": "Karlsruhe Institute of Technology",
            "attribution": null,
            "id": 29,
            "uuid": "0e972266-ccc9-4434-b4ab-e53c4586e511"
        },
        {
            "is_organisation": false,
            "first_name": "Pia",
            "last_name": "Ebeling",
            "organisation_name": null,
            "organisation_abbrev": null,
            "affiliation": "Helmholtz Centre for Environmental Research",
            "attribution": null,
            "id": 30,
            "uuid": "f07a1701-6b71-4d0a-bd2d-0ccca6bd49d1"
        },
        {
            "is_organisation": false,
            "first_name": "Björn",
            "last_name": "Guse",
            "organisation_name": null,
            "organisation_abbrev": null,
            "affiliation": " Helmholtz Centre Potsdam - GFZ German Research Centre for Geosciences, Kiel University",
            "attribution": null,
            "id": 31,
            "uuid": "da4eb160-d96a-4793-8a3a-f34ad47212cb"
        },
        {
            "is_organisation": false,
            "first_name": "Jonas",
            "last_name": "Götte",
            "organisation_name": null,
            "organisation_abbrev": null,
            "affiliation": "Swiss Federal Institute for Forest, Snow and Landscape Research",
            "attribution": null,
            "id": 32,
            "uuid": "88f4e14d-2255-42a7-9e7a-227fdb732174"
        },
        {
            "is_organisation": false,
            "first_name": "Sibylle",
            "last_name": "Hassler",
            "organisation_name": null,
            "organisation_abbrev": null,
            "affiliation": "Karlsruhe Institute of Technology",
            "attribution": null,
            "id": 33,
            "uuid": "f76b518f-6458-49e4-a042-5bd1d232968d"
        },
        {
            "is_organisation": false,
            "first_name": "Corina",
            "last_name": "Hauffe",
            "organisation_name": null,
            "organisation_abbrev": null,
            "affiliation": " TU Dresden",
            "attribution": null,
            "id": 34,
            "uuid": "b2203fb8-d2c7-47da-9e41-09bf8b0feaa6"
        },
        {
            "is_organisation": false,
            "first_name": "Jens",
            "last_name": "Kiesel",
            "organisation_name": null,
            "organisation_abbrev": null,
            "affiliation": "Kiel University",
            "attribution": null,
            "id": 35,
            "uuid": "768a6e60-1240-48d7-92cc-c2ee39e586e9"
        },
        {
            "is_organisation": false,
            "first_name": "Ingo",
            "last_name": "Heidbüchel",
            "organisation_name": null,
            "organisation_abbrev": null,
            "affiliation": "University of Bayreuth",
            "attribution": null,
            "id": 36,
            "uuid": "1be7306d-faa1-4502-9605-3e62b3479960"
        },
        {
            "is_organisation": false,
            "first_name": "Mirko",
            "last_name": "Mälicke",
            "organisation_name": null,
            "organisation_abbrev": null,
            "affiliation": "Karlsruhe Institute of Technology",
            "attribution": null,
            "id": 37,
            "uuid": "2b19d7d3-07cd-43c9-b056-7ff539699b38"
        },
        {
            "is_organisation": false,
            "first_name": "Hannes",
            "last_name": "Müller-Thomy",
            "organisation_name": null,
            "organisation_abbrev": null,
            "affiliation": "Technische Universität Braunschweig",
            "attribution": null,
            "id": 38,
            "uuid": "01fb00bf-f9f9-474a-aaae-be68fc115790"
        },
        {
            "is_organisation": false,
            "first_name": "Michael",
            "last_name": "Stölzle",
            "organisation_name": null,
            "organisation_abbrev": null,
            "affiliation": "University of Freiburg",
            "attribution": null,
            "id": 39,
            "uuid": "94519cdf-7dad-4761-a9df-71f21adc328b"
        },
        {
            "is_organisation": false,
            "first_name": "Larisa",
            "last_name": "Tarasova",
            "organisation_name": null,
            "organisation_abbrev": null,
            "affiliation": " Helmholtz Centre for Environmental Research",
            "attribution": null,
            "id": 40,
            "uuid": "e3adf27d-ed6b-4b01-bc5e-88c2467c3897"
        },
        {
            "is_organisation": false,
            "first_name": "Ralf",
            "last_name": "Loritz",
            "organisation_name": null,
            "organisation_abbrev": null,
            "affiliation": "Karlsruhe Institute of Technology",
            "attribution": null,
            "id": 41,
            "uuid": "0fbe1e11-c45a-42ad-87df-fde805e2aee4"
        }
    ],
    "keywords": [],
    "details": [],
    "datasource": {
        "path": "/data/qt7760/camels_de/timeseries_simulated/CAMELS_DE_discharge_sim_DE111360.csv",
        "encoding": "utf-8",
        "variable_names": [
            "discharge_spec_obs",
            "discharge_spec_sim_lstm"
        ],
        "args": {},
        "id": 4342,
        "type": {
            "title": "Local CSV File",
            "name": "csv",
            "description": "Standard csv file source on the database server machine",
            "id": 3
        },
        "temporal_scale": {
            "resolution": "PT1H",
            "observation_start": "1963-09-01T00:00:00",
            "observation_end": "2020-12-31T00:00:00",
            "support": 1.0,
            "dimension_names": [
                "date"
            ]
        },
        "spatial_scale": null
    }
}